nexus_python/__init__.py
nexus_python/nexusdb.py
nexus_python-0.3.1.dist-info/LICENSE
nexus_python-0.3.1.dist-info/METADATA
nexus_python-0.3.1.dist-info/WHEEL
nexus_python-0.3.1.dist-info/RECORD
