Metadata-Version: 2.1
Name: nexus-python
Version: 0.3.1
Summary: A simple interface for interacting with NexusDB.
License: MIT
Author: Will Humble
Author-email: w@astraanalytics.co
Requires-Python: >=3.11.8,<4.0.0
Classifier: License :: OSI Approved :: MIT License
Classifier: Programming Language :: Python :: 3
Classifier: Programming Language :: Python :: 3.12
Requires-Dist: requests (>=2.25.1,<3.0.0)
Requires-Dist: tabulate (>=0.9.0,<0.10.0)
